tokviz/__init__.py
tokviz/visualization.py
tokviz-0.1.dist-info/LICENSE
tokviz-0.1.dist-info/METADATA
tokviz-0.1.dist-info/WHEEL
tokviz-0.1.dist-info/top_level.txt
tokviz-0.1.dist-info/RECORD
