Metadata-Version: 2.1
Name: tokviz
Version: 0.1
Summary: Library for visualizing tokenization patterns across different language models
Home-page: https://github.com/Mr-DG-Wick/tokviz
Author: Deepak Gupta
Author-email: Deepak Gupta <deepak.gupta.h401@gmail.com>
Project-URL: Homepage, https://github.com/Mr-DG-Wick/tokviz
Classifier: Programming Language :: Python :: 3
Classifier: License :: OSI Approved :: MIT License
Classifier: Operating System :: OS Independent
Requires-Python: >=3.10
License-File: LICENSE
